xako/__init__.py
xako/client.py
xako/messages.py
xako/models.py
xako/views.py
xako/backends/__init__.py
xako/backends/email.py
xako/scripts/__init__.py
xako/scripts/base.py
xako/scripts/clean.py
xako/scripts/initializedb.py
xako/scripts/messages.py
xako/scripts/utils.py
xako/static/jquery.js
xako/static/underscore.js
xako/templates/domain.html
xako/templates/index.html
xako/utils/__init__.py
xako/utils/alchemy.py
xako/utils/allofthem.py
xako/utils/file.py
xako/utils/fingerprint.py
xako/utils/priority.py
xako/utils/settings.py
xako-0.7.0.dist-info/DESCRIPTION.rst
xako-0.7.0.dist-info/METADATA
xako-0.7.0.dist-info/RECORD
xako-0.7.0.dist-info/WHEEL
xako-0.7.0.dist-info/entry_points.txt
xako-0.7.0.dist-info/metadata.json
xako-0.7.0.dist-info/top_level.txt
